nsl/stac/__init__.py
nsl/stac/client.py
nsl/stac/enum.py
nsl/stac/experimental.py
nsl/stac/subscription.py
nsl/stac/utils.py
nsl/stac/destinations/__init__.py
nsl/stac/destinations/aws.py
nsl/stac/destinations/base.py
nsl/stac/destinations/gcp.py
nsl/stac/destinations/memory.py
nsl.stac-1.2.0.dist-info/LICENSE
nsl.stac-1.2.0.dist-info/METADATA
nsl.stac-1.2.0.dist-info/WHEEL
nsl.stac-1.2.0.dist-info/top_level.txt
nsl.stac-1.2.0.dist-info/RECORD
