Metadata-Version: 2.1
Name: nsl.stac
Version: 1.2.0
Summary: gRPC Spatio Temporal Asset Catalog library
Home-page: https://github.com/nearspacelabs/stac-client-python
Author: David Raleigh
Author-email: david@nearspacelabs.com
License: Apache 2.0
Platform: UNKNOWN
Classifier: Programming Language :: Python
Classifier: Programming Language :: Python :: 3
Classifier: Programming Language :: Python :: 3.6
Classifier: Programming Language :: Python :: 3.7
Requires-Python: >3.6.0
Requires-Dist: boto3
Requires-Dist: epl.protobuf.v1
Requires-Dist: google-cloud-storage
Requires-Dist: grpcio-tools
Requires-Dist: protobuf
Requires-Dist: requests
Requires-Dist: retry
